awslake/__init__.py
awslake/communicate_with_aws.py
awslake-1.1.17.dist-info/METADATA
awslake-1.1.17.dist-info/WHEEL
awslake-1.1.17.dist-info/top_level.txt
awslake-1.1.17.dist-info/RECORD
